cafaeval/__init__.py
cafaeval/__main__.py
cafaeval/evaluation.py
cafaeval/graph.py
cafaeval/parser.py
cafaeval/data/example/IDPO_disorder_function.obo
cafaeval/data/example/ground_truth.tsv
cafaeval/data/example/predictions/pred_1.tsv
cafaeval/data/example/predictions/pred_2.tsv
cafaeval/data/example/predictions/pred_3.tsv
cafaeval/data/example/predictions/pred_4.tsv
cafaeval/data/example/predictions/pred_5.tsv
cafaeval-1.3.0.dist-info/LICENCE.md
cafaeval-1.3.0.dist-info/METADATA
cafaeval-1.3.0.dist-info/WHEEL
cafaeval-1.3.0.dist-info/entry_points.txt
cafaeval-1.3.0.dist-info/top_level.txt
cafaeval-1.3.0.dist-info/RECORD
