Metadata-Version: 2.1
Name: cafaeval
Version: 1.3.0
Summary: CAFA evaluator code
Author-email: Damiano Piovesan <damiano.piovesan@unipd.it>, Parnal Joshi <parnal@iastate.edu>
License: GNU GENERAL PUBLIC LICENSE
Project-URL: Homepage, https://github.com/BioComputingUP/CAFA-evaluator
Project-URL: Repository, https://github.com/BioComputingUP/CAFA-evaluator
Project-URL: Changelog, https://github.com/BioComputingUP/CAFA-evaluator/blob/main/CHANGELOG.md
Project-URL: Wiki, https://github.com/BioComputingUP/CAFA-evaluator/wiki
Keywords: CAFA,structured data,ontology,Gene Ontology,protein function
Classifier: License :: OSI Approved :: GNU General Public License v3 (GPLv3)
Classifier: Programming Language :: Python :: 3
Classifier: Operating System :: OS Independent
Requires-Python: >=3.6
License-File: LICENCE.md
Requires-Dist: pandas
Requires-Dist: matplotlib
Requires-Dist: numpy
